ntncalculator/__init__.py
ntncalculator-0.1.dist-info/LICENSE.txt
ntncalculator-0.1.dist-info/METADATA
ntncalculator-0.1.dist-info/WHEEL
ntncalculator-0.1.dist-info/top_level.txt
ntncalculator-0.1.dist-info/RECORD
