Metadata-Version: 2.1
Name: ntncalculator
Version: 0.1
Summary: A useful module
Home-page: UNKNOWN
Author: Jitendra Choudhary
Author-email: asvvsb5254@gmail.com
License: UNKNOWN
Platform: UNKNOWN
License-File: LICENSE.txt
Requires-Dist: wheel
Requires-Dist: bar
Requires-Dist: greek
